btdripper/__init__.py
btdripper/btdripper.py
btdripper-0.1.0.post1.data/scripts/btdripper.py
btdripper-0.1.0.post1.dist-info/LICENSE
btdripper-0.1.0.post1.dist-info/METADATA
btdripper-0.1.0.post1.dist-info/WHEEL
btdripper-0.1.0.post1.dist-info/top_level.txt
btdripper-0.1.0.post1.dist-info/RECORD
