Metadata-Version: 2.1
Name: btdripper
Version: 0.1.0.post1
Summary: Control a Kamoer Dripping Pro pump
Home-page: https://github.com/lalten/btdripper
Author: Laurenz Altenmüller
Author-email: pypi@laure.nz
License: MIT
Platform: UNKNOWN
Requires-Dist: gatt
Requires-Dist: dbus-python
